client/__init__.py
client/client.py
client/client/__init__.py
client/client/add_contact.py
client/client/del_contact.py
client/client/main_window.py
client/client/main_window_conv.py
client/client/start_dialog.py
client/client/transport.py
client/common/__init__.py
client/common/config.py
client/common/decorators.py
client/common/descrptrs.py
client/common/errors.py
client/common/jim.py
client/common/metaclasses.py
client/common/utils.py
client/database/__init__.py
client/database/client_database.py
client/logs/__init__.py
client/logs/config_client_log.py
client/logs/config_server_log.py
client/unit_tests/__init__.py
client/unit_tests/test_client.py
client/unit_tests/test_server.py
client/unit_tests/test_utils.py
messenger_client_app-0.0.1.dist-info/METADATA
messenger_client_app-0.0.1.dist-info/WHEEL
messenger_client_app-0.0.1.dist-info/top_level.txt
messenger_client_app-0.0.1.dist-info/RECORD
