Metadata-Version: 2.1
Name: messenger-client-app
Version: 0.0.1
Summary: Messenger Client
Home-page: UNKNOWN
Author: Minor Anatolii
Author-email: anminor91@gmail.com
License: UNKNOWN
Platform: UNKNOWN
Requires-Dist: PyQt5
Requires-Dist: pycryptodome
Requires-Dist: pycryptodomex
Requires-Dist: sqlalchemy
